baselines/__init__.py
baselines/ppo/__init__.py
baselines/ppo/ppo_memtasks.py
baselines/ppo/ppo_memtasks_lstm.py
mikasa_robo_suite/__init__.py
mikasa_robo_suite/dataset_collectors/__init__.py
mikasa_robo_suite/dataset_collectors/get_dataset_collectors_ckpt.py
mikasa_robo_suite/dataset_collectors/get_mikasa_robo_datasets.py
mikasa_robo_suite/dataset_collectors/parallel_dataset_collection_manager.py
mikasa_robo_suite/dataset_collectors/parallel_training_manager.py
mikasa_robo_suite/memory_envs/__init__.py
mikasa_robo_suite/memory_envs/bunch_of_colors.py
mikasa_robo_suite/memory_envs/chain_of_colors.py
mikasa_robo_suite/memory_envs/intercept.py
mikasa_robo_suite/memory_envs/intercept_grab.py
mikasa_robo_suite/memory_envs/remember_color.py
mikasa_robo_suite/memory_envs/remember_shape.py
mikasa_robo_suite/memory_envs/remember_shape_and_color.py
mikasa_robo_suite/memory_envs/rotate_lenient.py
mikasa_robo_suite/memory_envs/rotate_strict.py
mikasa_robo_suite/memory_envs/seq_of_colors.py
mikasa_robo_suite/memory_envs/shell_game_pick.py
mikasa_robo_suite/memory_envs/shell_game_push.py
mikasa_robo_suite/memory_envs/shell_game_touch.py
mikasa_robo_suite/memory_envs/take_it_back.py
mikasa_robo_suite/utils/__init__.py
mikasa_robo_suite/utils/shapes.py
mikasa_robo_suite/utils/wrappers.py
mikasa_robo_suite-0.0.5.dist-info/LICENSE
mikasa_robo_suite-0.0.5.dist-info/METADATA
mikasa_robo_suite-0.0.5.dist-info/WHEEL
mikasa_robo_suite-0.0.5.dist-info/top_level.txt
mikasa_robo_suite-0.0.5.dist-info/RECORD
